odoo10_addon_base_tier_validation-10.0.1.0.1-py2.7-nspkg.pth
odoo/addons/base_tier_validation/README.rst
odoo/addons/base_tier_validation/__init__.py
odoo/addons/base_tier_validation/__manifest__.py
odoo/addons/base_tier_validation/i18n/base_tier_validation.pot
odoo/addons/base_tier_validation/models/__init__.py
odoo/addons/base_tier_validation/models/tier_definition.py
odoo/addons/base_tier_validation/models/tier_review.py
odoo/addons/base_tier_validation/models/tier_validation.py
odoo/addons/base_tier_validation/security/ir.model.access.csv
odoo/addons/base_tier_validation/views/tier_definition_view.xml
odoo/addons/base_tier_validation/views/tier_review_view.xml
odoo10_addon_base_tier_validation-10.0.1.0.1.dist-info/DESCRIPTION.rst
odoo10_addon_base_tier_validation-10.0.1.0.1.dist-info/METADATA
odoo10_addon_base_tier_validation-10.0.1.0.1.dist-info/RECORD
odoo10_addon_base_tier_validation-10.0.1.0.1.dist-info/WHEEL
odoo10_addon_base_tier_validation-10.0.1.0.1.dist-info/metadata.json
odoo10_addon_base_tier_validation-10.0.1.0.1.dist-info/namespace_packages.txt
odoo10_addon_base_tier_validation-10.0.1.0.1.dist-info/top_level.txt
